README.md
setup.py
bin/view-larcv.py
bin/view3D-larcv.py
src/datatypes/__init__.py
src/datatypes/bbox2d.py
src/datatypes/bbox3d.py
src/datatypes/cluster2d.py
src/datatypes/cluster3d.py
src/datatypes/connectedObjects.py
src/datatypes/database.py
src/datatypes/drawableItems.py
src/datatypes/image2d.py
src/datatypes/particle2d.py
src/datatypes/particle3d.py
src/datatypes/pixel2d.py
src/datatypes/sparse2d.py
src/datatypes/sparse3d.py
src/gui/__init__.py
src/gui/evdgui.py
src/gui/evdgui3D.py
src/gui/gui.py
src/gui/gui3D.py
src/gui/recobox.py
src/gui/view_manager.py
src/gui/view_manager3D.py
src/gui/viewport.py
src/gui/viewport3D.py
src/larcv_viewer.egg-info/PKG-INFO
src/larcv_viewer.egg-info/SOURCES.txt
src/larcv_viewer.egg-info/dependency_links.txt
src/larcv_viewer.egg-info/requires.txt
src/larcv_viewer.egg-info/top_level.txt
src/manager/__init__.py
src/manager/evd_manager_2D.py
src/manager/evd_manager_3D.py
src/manager/evd_manager_base.py
src/manager/event_meta.py