Metadata-Version: 2.1
Name: larcv-viewer
Version: 1.0.0
Summary: Graphic Visualization Tool for larcv files
Home-page: https://github.com/DeepLearnPhysics/larcv-viewer
Author: Corey Adams, DeepLearnPhysics
License: UNKNOWN
Project-URL: Bug Reports, https://github.com/DeepLearnPhysics/larcv-viewer/issues
Project-URL: larcv, https://github.com/DeepLearnPhysics/larcv3/
Project-URL: Source, https://github.com/DeepLearnPhysics/larcv-viewer/
Keywords: larcv,pyqt5,pyqtgraph,PyOpenGL,numpy
Platform: UNKNOWN
Classifier: Intended Audience :: Developers
Classifier: License :: OSI Approved :: MIT License
Classifier: Programming Language :: Python :: 3
Requires-Python: >=3.6, <4
